setup.cfg
setup.py
coffee/__init__.py
coffee/mixins.py
django_coffee.egg-info/PKG-INFO
django_coffee.egg-info/SOURCES.txt
django_coffee.egg-info/dependency_links.txt
django_coffee.egg-info/not-zip-safe
django_coffee.egg-info/top_level.txt