Metadata-Version: 1.0
Name: django-coffee
Version: 0.0.4
Summary: Django Coffee
Home-page: https://github.com/jacothiart/django-coffee
Author: Jaco Thiart
Author-email: jaco@jacothiart.com
License: MIT
Platform: UNKNOWN
